<?xml version="1.0" encoding="UTF-8"?><root><pages><page><UUID>74A6CD0D600349B7A9DBD58B27FFF56C</UUID><dateTime tmz="0">2019-01-03 04:33:43</dateTime><pageName name="home"><![CDATA[home.html]]></pageName><pagePath/><PageOrder><![CDATA[0]]></PageOrder></page><page><UUID>F65CCD94E8A94B03BD7DF5C73F855DEA</UUID><dateTime tmz="0">2018-12-02 06:30:04</dateTime><pageName name="music"><![CDATA[music.html]]></pageName><pagePath><![CDATA[music.html]]></pagePath><PageOrder><![CDATA[1]]></PageOrder></page><page><UUID>21C9185A296F4DBC8144F3B5559B15D3</UUID><dateTime tmz="0">2019-01-03 04:33:43</dateTime><pageName name="contact"><![CDATA[contact.html]]></pageName><pagePath/><PageOrder><![CDATA[2]]></PageOrder></page><page><UUID>BE9C0E0910C945A3BC493FA815EBAB9A</UUID><dateTime tmz="0">2018-12-02 06:30:04</dateTime><pageName name="imprint"><![CDATA[imprint.html]]></pageName><pagePath><![CDATA[imprint.html]]></pagePath><PageOrder><![CDATA[3]]></PageOrder></page></pages><siteData><siteheadercode></siteheadercode><sitefootercode></sitefootercode></siteData></root>